liquidcss/__init__.py
liquidcss/__main__.py
liquidcss/cli.py
liquidcss/parsers.py
liquidcss/settings.py
liquidcss/stager.py
liquidcss/utils.py
liquidcss/workspace.py
liquidcss/commands/__init__.py
liquidcss/commands/deploy.py
liquidcss/commands/drop.py
liquidcss/commands/grab.py
liquidcss/commands/init.py
liquidcss/commands/stage.py
liquidcss/commands/status.py
liquidcss-1.0.2.dist-info/LICENSE.TXT
liquidcss-1.0.2.dist-info/METADATA
liquidcss-1.0.2.dist-info/WHEEL
liquidcss-1.0.2.dist-info/entry_points.txt
liquidcss-1.0.2.dist-info/top_level.txt
liquidcss-1.0.2.dist-info/RECORD
