Metadata-Version: 2.1
Name: liquidcss
Version: 1.0.2
Summary: Alters css selector names across css files and html templates.
Home-page: https://github.com/sarartur/liquidcss
Author: Artur Saradzhyan
Author-email: saradzhyanartur@gmail.com
License: UNKNOWN
Platform: UNKNOWN
Classifier: Programming Language :: Python :: 3
Classifier: License :: OSI Approved :: MIT License
Classifier: Operating System :: OS Independent
Requires-Python: >=3.6
Requires-Dist: cssutils (==1.0.2)
Requires-Dist: bs4 (==0.0.1)
Requires-Dist: esprima (==4.0.1)
